benchmarks/__init__.py
benchmarks/benchmark_suite.py
feature_engineering_tk/__init__.py
feature_engineering_tk/base.py
feature_engineering_tk/data_analysis.py
feature_engineering_tk/exceptions.py
feature_engineering_tk/feature_engineering.py
feature_engineering_tk/feature_selection.py
feature_engineering_tk/preprocessing.py
feature_engineering_tk/statistical_utils.py
feature_engineering_tk/utils.py
feature_engineering_tk-2.4.3.dist-info/licenses/LICENSE
feature_engineering_tk-2.4.3.dist-info/METADATA
feature_engineering_tk-2.4.3.dist-info/WHEEL
feature_engineering_tk-2.4.3.dist-info/top_level.txt
feature_engineering_tk-2.4.3.dist-info/RECORD
