Metadata-Version: 2.4
Name: feature-engineering-tk
Version: 2.4.3
Summary: Feature Engineering Toolkit - A comprehensive Python library for feature engineering and data analysis
Home-page: https://github.com/bluelion1999/feature_engineering_tk
Author: bluelion1999
Author-email: 
License: MIT
Project-URL: Homepage, https://github.com/bluelion1999/feature_engineering_tk
Project-URL: Bug Tracker, https://github.com/bluelion1999/feature_engineering_tk/issues
Project-URL: Source Code, https://github.com/bluelion1999/feature_engineering_tk
Keywords: machine-learning,feature-engineering,data-analysis,preprocessing,feature-selection
Classifier: Development Status :: 4 - Beta
Classifier: Intended Audience :: Developers
Classifier: Intended Audience :: Science/Research
Classifier: Topic :: Scientific/Engineering :: Artificial Intelligence
Classifier: Topic :: Software Development :: Libraries :: Python Modules
Classifier: License :: OSI Approved :: MIT License
Classifier: Programming Language :: Python :: 3
Classifier: Programming Language :: Python :: 3.8
Classifier: Programming Language :: Python :: 3.9
Classifier: Programming Language :: Python :: 3.10
Classifier: Programming Language :: Python :: 3.11
Classifier: Programming Language :: Python :: 3.12
Requires-Python: >=3.8
License-File: LICENSE
Requires-Dist: pandas>=1.5.0
Requires-Dist: numpy>=1.23.0
Requires-Dist: scikit-learn>=1.2.0
Requires-Dist: scipy>=1.9.0
Requires-Dist: matplotlib>=3.6.0
Requires-Dist: seaborn>=0.12.0
Requires-Dist: statsmodels>=0.14.0
Provides-Extra: dev
Requires-Dist: pytest>=7.0; extra == "dev"
Requires-Dist: pytest-cov>=4.0; extra == "dev"
Requires-Dist: black>=23.0; extra == "dev"
Requires-Dist: flake8>=6.0; extra == "dev"
Requires-Dist: mypy>=1.0; extra == "dev"
Dynamic: home-page
Dynamic: license-file
Dynamic: requires-python
